dbconnectionlib/__init__.py
dbconnectionlib/start_connections.py
dbconnectionlib-0.1.0.dist-info/METADATA
dbconnectionlib-0.1.0.dist-info/WHEEL
dbconnectionlib-0.1.0.dist-info/top_level.txt
dbconnectionlib-0.1.0.dist-info/RECORD
