Metadata-Version: 2.1
Name: dbconnectionlib
Version: 0.1.0
Summary: DB Connection Python library
Home-page: https://gitlab.td.gfk.com/Divya.Ravindran/db-connections
Author: Divya Ravindran
Author-email: divya.ravindran@gfk.com
License: UNKNOWN
Platform: UNKNOWN
Classifier: Programming Language :: Python :: 3
Classifier: License :: OSI Approved :: MIT License
Classifier: Operating System :: OS Independent
Requires-Python: >=3.5
Requires-Dist: sqlalchemy
